ipyturtlenext.py
ipyturtlenext-0.1.1.dist-info/LICENSE
ipyturtlenext-0.1.1.dist-info/METADATA
ipyturtlenext-0.1.1.dist-info/WHEEL
ipyturtlenext-0.1.1.dist-info/top_level.txt
ipyturtlenext-0.1.1.dist-info/RECORD
