Metadata-Version: 2.1
Name: ipyturtlenext
Version: 0.1.1
Summary: Creating Turtle Graphics in IPython/Jupyter with ipycanvas
Home-page: https://github.com/Python-Ninja-Hebi/ipython-turtle-next
Author: python-ninja
Author-email: hebi@python-ninja.com
License: MIT
Keywords: turtle,graphics,ipycanvas,ipywidget
Platform: UNKNOWN
Classifier: Development Status :: 4 - Beta
Classifier: Intended Audience :: Developers
Classifier: Topic :: Multimedia :: Graphics
Classifier: License :: OSI Approved :: MIT License
Classifier: Programming Language :: Python :: 3
Classifier: Programming Language :: Python :: 3.3
Classifier: Programming Language :: Python :: 3.4
Classifier: Programming Language :: Python :: 3.5
Classifier: Programming Language :: Python :: 3.6
Classifier: Programming Language :: Python :: 3.7
Classifier: Programming Language :: Python :: 3.8
Classifier: Programming Language :: Python :: 3.9
License-File: LICENSE
Requires-Dist: ipycanvas
